{
  "fold_scores": [
    {
      "tick": 200,
      "recall_rate": 0.6748466257668712,
      "precision_rate": 0.25398773006134967,
      "activation_recall_correlation": 0.9756686275604598,
      "fact_episode_delta": 0.35706214689265536,
      "forgetting_curve_smoothness": 0.0039186028201977086,
      "storage_std": 0.1915035354660556,
      "storage_iqr": 0.29658790572015753,
      "storage_gini": 0.20600833970594323,
      "retrieval_std": 0.19147634394951468,
      "retrieval_iqr": 0.29658790572015753,
      "retrieval_gini": 0.20599162875892915,
      "activation_std": 0.1915035354660556,
      "activation_iqr": 0.29658790572015753,
      "activation_gini": 0.20600833970594323,
      "threshold_metrics": {
        "0.1": {
          "recall_rate": 0.6748466257668712,
          "precision_rate": 0.25398773006134967
        },
        "0.2": {
          "recall_rate": 0.6748466257668712,
          "precision_rate": 0.25398773006134967
        },
        "0.3": {
          "recall_rate": 0.6748466257668712,
          "precision_rate": 0.25398773006134967
        },
        "0.4": {
          "recall_rate": 0.6748466257668712,
          "precision_rate": 0.2552147239263804
        },
        "0.5": {
          "recall_rate": 0.6748466257668712,
          "precision_rate": 0.2552147239263804
        },
        "0.6": {
          "recall_rate": 0.6809815950920245,
          "precision_rate": 0.2588957055214724
        },
        "0.7": {
          "recall_rate": 0.7177914110429447,
          "precision_rate": 0.20613496932515338
        },
        "0.8": {
          "recall_rate": 0.6871165644171779,
          "precision_rate": 0.1901840490797546
        },
        "0.9": {
          "recall_rate": 0.6748466257668712,
          "precision_rate": 0.16809815950920245
        }
      },
      "recall_mean": 0.6816632583503748,
      "precision_mean": 0.23285616905248807,
      "threshold_discrimination": 0.042944785276073594,
      "threshold_summary": {
        "threshold_auc": 0.6816632583503748,
        "slope": 0.0
      },
      "corr_mean": 0.7660713032656041,
      "corr_score": 0.7660713032656041,
      "smoothness_score": 0.9608139717980229,
      "retrieval_score": 0.6189331970006817,
      "forgetting_score": 0.5162614656152003,
      "non_target_mean_storage": 0.4837385343847998,
      "plausibility_score": 0.7660713032656041,
      "overall_score": 0.6197826175819938,
      "composite_score": 0.6197826175819938,
      "mrr_mean": 0.5422631220177233,
      "precision_strict": 0.136332651670075,
      "precision_lift": 2.7755575615628914e-17,
      "precision_associative": 0.23285616905248807,
      "similarity_recall_rate": 0.6748466257668712,
      "retention_curve": {
        "40": 1.0,
        "80": 1.0,
        "120": 0.8125,
        "160": 0.6558441558441559,
        "200": 0.6748466257668712
      },
      "retention_auc": 0.8286381563222054,
      "selectivity_score": 0.03980913428766192,
      "robustness_score": 0.0
    },
    {
      "tick": 200,
      "recall_rate": 0.6415094339622641,
      "precision_rate": 0.24779874213836478,
      "activation_recall_correlation": 0.9227252998841149,
      "fact_episode_delta": 0.28954128440366966,
      "forgetting_curve_smoothness": 0.10538013862780984,
      "storage_std": 0.19051462026127433,
      "storage_iqr": 0.29658790572015753,
      "storage_gini": 0.20530895232839555,
      "retrieval_std": 0.19051315085391748,
      "retrieval_iqr": 0.29658790572015753,
      "retrieval_gini": 0.20530789117434728,
      "activation_std": 0.19051462026127433,
      "activation_iqr": 0.29658790572015753,
      "activation_gini": 0.20530895232839555,
      "threshold_metrics": {
        "0.1": {
          "recall_rate": 0.6415094339622641,
          "precision_rate": 0.24779874213836478
        },
        "0.2": {
          "recall_rate": 0.6415094339622641,
          "precision_rate": 0.24779874213836478
        },
        "0.3": {
          "recall_rate": 0.6415094339622641,
          "precision_rate": 0.24779874213836478
        },
        "0.4": {
          "recall_rate": 0.6477987421383647,
          "precision_rate": 0.25031446540880503
        },
        "0.5": {
          "recall_rate": 0.6477987421383647,
          "precision_rate": 0.25031446540880503
        },
        "0.6": {
          "recall_rate": 0.6477987421383647,
          "precision_rate": 0.25031446540880503
        },
        "0.7": {
          "recall_rate": 0.6792452830188679,
          "precision_rate": 0.2
        },
        "0.8": {
          "recall_rate": 0.6729559748427673,
          "precision_rate": 0.19119496855345913
        },
        "0.9": {
          "recall_rate": 0.6415094339622641,
          "precision_rate": 0.15471698113207547
        }
      },
      "recall_mean": 0.6512928022361986,
      "precision_mean": 0.22669461914744934,
      "threshold_discrimination": 0.037735849056603765,
      "threshold_summary": {
        "threshold_auc": 0.6512928022361986,
        "slope": 0.0
      },
      "corr_mean": 0.831665322001962,
      "corr_score": 0.831665322001962,
      "smoothness_score": 0.0,
      "retrieval_score": 0.5825506638714187,
      "forgetting_score": 0.5167707566574313,
      "non_target_mean_storage": 0.4832292433425686,
      "plausibility_score": 0.831665322001962,
      "overall_score": 0.621806360879159,
      "composite_score": 0.621806360879159,
      "mrr_mean": 0.49853249475890987,
      "precision_strict": 0.13025856044723969,
      "precision_lift": 0.0,
      "precision_associative": 0.22669461914744934,
      "similarity_recall_rate": 0.6415094339622641,
      "retention_curve": {
        "40": 0.0,
        "80": 1.0,
        "120": 0.7,
        "160": 0.6275862068965518,
        "200": 0.6415094339622641
      },
      "retention_auc": 0.5938191281717631,
      "selectivity_score": 0.033822501747030026,
      "robustness_score": 0.0
    },
    {
      "tick": 200,
      "recall_rate": 0.5833333333333334,
      "precision_rate": 0.24,
      "activation_recall_correlation": 0.9368452801871586,
      "fact_episode_delta": 0.25963636363636367,
      "forgetting_curve_smoothness": 0.10694779634606313,
      "storage_std": 0.19105176983373362,
      "storage_iqr": 0.29658790572015753,
      "storage_gini": 0.20570519238489007,
      "retrieval_std": 0.19099053171878738,
      "retrieval_iqr": 0.29658790572015753,
      "retrieval_gini": 0.20566814919491347,
      "activation_std": 0.19105176983373362,
      "activation_iqr": 0.29658790572015753,
      "activation_gini": 0.20570519238489007,
      "threshold_metrics": {
        "0.1": {
          "recall_rate": 0.5833333333333334,
          "precision_rate": 0.24
        },
        "0.2": {
          "recall_rate": 0.5833333333333334,
          "precision_rate": 0.24
        },
        "0.3": {
          "recall_rate": 0.5833333333333334,
          "precision_rate": 0.24
        },
        "0.4": {
          "recall_rate": 0.5888888888888889,
          "precision_rate": 0.24555555555555555
        },
        "0.5": {
          "recall_rate": 0.5888888888888889,
          "precision_rate": 0.24555555555555555
        },
        "0.6": {
          "recall_rate": 0.5944444444444444,
          "precision_rate": 0.24666666666666667
        },
        "0.7": {
          "recall_rate": 0.6166666666666667,
          "precision_rate": 0.1922222222222222
        },
        "0.8": {
          "recall_rate": 0.6055555555555555,
          "precision_rate": 0.1811111111111111
        },
        "0.9": {
          "recall_rate": 0.5833333333333334,
          "precision_rate": 0.1511111111111111
        }
      },
      "recall_mean": 0.5919753086419753,
      "precision_mean": 0.2202469135802469,
      "threshold_discrimination": 0.033333333333333326,
      "threshold_summary": {
        "threshold_auc": 0.5919753086419753,
        "slope": 0.0
      },
      "corr_mean": 0.803340780337647,
      "corr_score": 0.803340780337647,
      "smoothness_score": 0.0,
      "retrieval_score": 0.5375864197530864,
      "forgetting_score": 0.5174232447276573,
      "non_target_mean_storage": 0.4825767552723427,
      "plausibility_score": 0.803340780337647,
      "overall_score": 0.5969678986403264,
      "composite_score": 0.5969678986403264,
      "mrr_mean": 0.47111111111111115,
      "precision_strict": 0.11839506172839506,
      "precision_lift": 0.0,
      "precision_associative": 0.2202469135802469,
      "similarity_recall_rate": 0.5833333333333334,
      "retention_curve": {
        "40": 1.0,
        "80": 1.0,
        "120": 0.5833333333333334,
        "160": 0.5443786982248521,
        "200": 0.5833333333333334
      },
      "retention_auc": 0.7422090729783039,
      "selectivity_score": 0.01654320987654323,
      "robustness_score": 0.0
    },
    {
      "tick": 200,
      "recall_rate": 0.5985915492957746,
      "precision_rate": 0.24647887323943662,
      "activation_recall_correlation": 0.9523596536046561,
      "fact_episode_delta": 0.3924398625429554,
      "forgetting_curve_smoothness": 0.031047281581340604,
      "storage_std": 0.18878347112768662,
      "storage_iqr": 0.29658790572015753,
      "storage_gini": 0.20400667395721536,
      "retrieval_std": 0.1887731432637758,
      "retrieval_iqr": 0.29658790572015753,
      "retrieval_gini": 0.20399880177518243,
      "activation_std": 0.18878347112768662,
      "activation_iqr": 0.29658790572015753,
      "activation_gini": 0.20400667395721536,
      "threshold_metrics": {
        "0.1": {
          "recall_rate": 0.5985915492957746,
          "precision_rate": 0.24647887323943662
        },
        "0.2": {
          "recall_rate": 0.5985915492957746,
          "precision_rate": 0.24647887323943662
        },
        "0.3": {
          "recall_rate": 0.5985915492957746,
          "precision_rate": 0.24647887323943662
        },
        "0.4": {
          "recall_rate": 0.6126760563380281,
          "precision_rate": 0.2507042253521127
        },
        "0.5": {
          "recall_rate": 0.6126760563380281,
          "precision_rate": 0.2507042253521127
        },
        "0.6": {
          "recall_rate": 0.6197183098591549,
          "precision_rate": 0.2591549295774648
        },
        "0.7": {
          "recall_rate": 0.6549295774647887,
          "precision_rate": 0.20140845070422536
        },
        "0.8": {
          "recall_rate": 0.6197183098591549,
          "precision_rate": 0.18732394366197183
        },
        "0.9": {
          "recall_rate": 0.6056338028169014,
          "precision_rate": 0.15492957746478872
        }
      },
      "recall_mean": 0.6134585289514866,
      "precision_mean": 0.22707355242566507,
      "threshold_discrimination": 0.05633802816901412,
      "threshold_summary": {
        "threshold_auc": 0.6134585289514866,
        "slope": 0.007042253521126751
      },
      "corr_mean": 0.7837877687989061,
      "corr_score": 0.7837877687989061,
      "smoothness_score": 0.689527184186594,
      "retrieval_score": 0.5594151017214397,
      "forgetting_score": 0.5159677099550394,
      "non_target_mean_storage": 0.4840322900449606,
      "plausibility_score": 0.7837877687989061,
      "overall_score": 0.6003016813725661,
      "composite_score": 0.6003016813725661,
      "mrr_mean": 0.49336202399582685,
      "precision_strict": 0.12269170579029735,
      "precision_lift": 4.163336342344337e-17,
      "precision_associative": 0.22707355242566507,
      "similarity_recall_rate": 0.5985915492957746,
      "retention_curve": {
        "40": 0.0,
        "80": 0.75,
        "120": 0.5714285714285714,
        "160": 0.56,
        "200": 0.5985915492957746
      },
      "retention_auc": 0.4960040241448692,
      "selectivity_score": 0.018309859154929636,
      "robustness_score": 0.0
    },
    {
      "tick": 200,
      "recall_rate": 0.6368421052631579,
      "precision_rate": 0.26210526315789473,
      "activation_recall_correlation": 0.926578496562221,
      "fact_episode_delta": 0.2497387669801463,
      "forgetting_curve_smoothness": 0.10317273352643683,
      "storage_std": 0.1924587810585427,
      "storage_iqr": 0.29658790572015753,
      "storage_gini": 0.2068053487795664,
      "retrieval_std": 0.1923296377981832,
      "retrieval_iqr": 0.29658790572015753,
      "retrieval_gini": 0.2067238495952585,
      "activation_std": 0.1924587810585427,
      "activation_iqr": 0.29658790572015753,
      "activation_gini": 0.2068053487795664,
      "threshold_metrics": {
        "0.1": {
          "recall_rate": 0.6368421052631579,
          "precision_rate": 0.26210526315789473
        },
        "0.2": {
          "recall_rate": 0.6368421052631579,
          "precision_rate": 0.26210526315789473
        },
        "0.3": {
          "recall_rate": 0.6368421052631579,
          "precision_rate": 0.26210526315789473
        },
        "0.4": {
          "recall_rate": 0.6368421052631579,
          "precision_rate": 0.2631578947368421
        },
        "0.5": {
          "recall_rate": 0.6368421052631579,
          "precision_rate": 0.2631578947368421
        },
        "0.6": {
          "recall_rate": 0.6421052631578947,
          "precision_rate": 0.26526315789473687
        },
        "0.7": {
          "recall_rate": 0.6578947368421053,
          "precision_rate": 0.21157894736842106
        },
        "0.8": {
          "recall_rate": 0.6526315789473685,
          "precision_rate": 0.20421052631578948
        },
        "0.9": {
          "recall_rate": 0.6473684210526316,
          "precision_rate": 0.17157894736842105
        }
      },
      "recall_mean": 0.6426900584795321,
      "precision_mean": 0.24058479532163743,
      "threshold_discrimination": 0.021052631578947434,
      "threshold_summary": {
        "threshold_auc": 0.6426900584795321,
        "slope": 0.010526315789473717
      },
      "corr_mean": 0.8425024887899429,
      "corr_score": 0.8425024887899429,
      "smoothness_score": 0.0,
      "retrieval_score": 0.5702909356725147,
      "forgetting_score": 0.5180896030433303,
      "non_target_mean_storage": 0.4819103969566697,
      "plausibility_score": 0.8425024887899429,
      "overall_score": 0.6200733575316572,
      "composite_score": 0.6200733575316572,
      "mrr_mean": 0.4818031189083821,
      "precision_strict": 0.12853801169590642,
      "precision_lift": 0.0,
      "precision_associative": 0.24058479532163743,
      "similarity_recall_rate": 0.6368421052631579,
      "retention_curve": {
        "40": 1.0,
        "80": 1.0,
        "120": 0.625,
        "160": 0.6149425287356322,
        "200": 0.6368421052631579
      },
      "retention_auc": 0.775356926799758,
      "selectivity_score": 0.016491228070175418,
      "robustness_score": 0.0
    }
  ],
  "k": 5,
  "mean": {
    "overall_score": 0.6117863832011405,
    "retrieval_score": 0.5737552636038282,
    "forgetting_score": 0.5169025559997318,
    "plausibility_score": 0.8054735326388125,
    "recall_mean": 0.6362159913319134,
    "mrr_mean": 0.4974143741583907,
    "corr_score": 0.8054735326388125,
    "retention_auc": 0.6872054616833798,
    "selectivity_score": 0.024995186627268046,
    "robustness_score": 0.0
  },
  "std": {
    "overall_score": 0.012088212453321177,
    "retrieval_score": 0.030183736548867645,
    "forgetting_score": 0.0008634961653289689,
    "plausibility_score": 0.03195508601523071,
    "recall_mean": 0.03467642553230906,
    "mrr_mean": 0.02722432211039712,
    "corr_score": 0.03195508601523071,
    "retention_auc": 0.13791145907246277,
    "selectivity_score": 0.011020677872259172,
    "robustness_score": 0.0
  },
  "worst_fold": {
    "tick": 200,
    "recall_rate": 0.5833333333333334,
    "precision_rate": 0.24,
    "activation_recall_correlation": 0.9368452801871586,
    "fact_episode_delta": 0.25963636363636367,
    "forgetting_curve_smoothness": 0.10694779634606313,
    "storage_std": 0.19105176983373362,
    "storage_iqr": 0.29658790572015753,
    "storage_gini": 0.20570519238489007,
    "retrieval_std": 0.19099053171878738,
    "retrieval_iqr": 0.29658790572015753,
    "retrieval_gini": 0.20566814919491347,
    "activation_std": 0.19105176983373362,
    "activation_iqr": 0.29658790572015753,
    "activation_gini": 0.20570519238489007,
    "threshold_metrics": {
      "0.1": {
        "recall_rate": 0.5833333333333334,
        "precision_rate": 0.24
      },
      "0.2": {
        "recall_rate": 0.5833333333333334,
        "precision_rate": 0.24
      },
      "0.3": {
        "recall_rate": 0.5833333333333334,
        "precision_rate": 0.24
      },
      "0.4": {
        "recall_rate": 0.5888888888888889,
        "precision_rate": 0.24555555555555555
      },
      "0.5": {
        "recall_rate": 0.5888888888888889,
        "precision_rate": 0.24555555555555555
      },
      "0.6": {
        "recall_rate": 0.5944444444444444,
        "precision_rate": 0.24666666666666667
      },
      "0.7": {
        "recall_rate": 0.6166666666666667,
        "precision_rate": 0.1922222222222222
      },
      "0.8": {
        "recall_rate": 0.6055555555555555,
        "precision_rate": 0.1811111111111111
      },
      "0.9": {
        "recall_rate": 0.5833333333333334,
        "precision_rate": 0.1511111111111111
      }
    },
    "recall_mean": 0.5919753086419753,
    "precision_mean": 0.2202469135802469,
    "threshold_discrimination": 0.033333333333333326,
    "threshold_summary": {
      "threshold_auc": 0.5919753086419753,
      "slope": 0.0
    },
    "corr_mean": 0.803340780337647,
    "corr_score": 0.803340780337647,
    "smoothness_score": 0.0,
    "retrieval_score": 0.5375864197530864,
    "forgetting_score": 0.5174232447276573,
    "non_target_mean_storage": 0.4825767552723427,
    "plausibility_score": 0.803340780337647,
    "overall_score": 0.5969678986403264,
    "composite_score": 0.5969678986403264,
    "mrr_mean": 0.47111111111111115,
    "precision_strict": 0.11839506172839506,
    "precision_lift": 0.0,
    "precision_associative": 0.2202469135802469,
    "similarity_recall_rate": 0.5833333333333334,
    "retention_curve": {
      "40": 1.0,
      "80": 1.0,
      "120": 0.5833333333333334,
      "160": 0.5443786982248521,
      "200": 0.5833333333333334
    },
    "retention_auc": 0.7422090729783039,
    "selectivity_score": 0.01654320987654323,
    "robustness_score": 0.0
  },
  "fold_deltas": [
    0.007996234380853284,
    0.010019977678018432,
    -0.014818484560814138,
    -0.011484701828574417,
    0.008286974330516617
  ]
}