{
  "status": "completed",
  "tick": 200,
  "recall_rate": 0.5228758169934641,
  "precision_rate": 0.17124183006535948,
  "activation_recall_correlation": 0.9484715349394428,
  "fact_episode_delta": 0.543452380952381,
  "forgetting_curve_smoothness": 0.015674906254667158,
  "storage_std": 0.2908387193048458,
  "storage_iqr": 0.5142203271756539,
  "storage_gini": 0.5092176512178016,
  "retrieval_std": 0.2898728572068804,
  "retrieval_iqr": 0.5142203271756539,
  "retrieval_gini": 0.5085714885000291,
  "activation_std": 0.2908387193048458,
  "activation_iqr": 0.5142203271756539,
  "activation_gini": 0.5092176512178016,
  "threshold_metrics": {
    "0.1": {
      "recall_rate": 0.5228758169934641,
      "precision_rate": 0.17124183006535948
    },
    "0.2": {
      "recall_rate": 0.5228758169934641,
      "precision_rate": 0.17124183006535948
    },
    "0.3": {
      "recall_rate": 0.5228758169934641,
      "precision_rate": 0.17124183006535948
    },
    "0.4": {
      "recall_rate": 0.5228758169934641,
      "precision_rate": 0.17124183006535948
    },
    "0.5": {
      "recall_rate": 0.5228758169934641,
      "precision_rate": 0.17124183006535948
    },
    "0.6": {
      "recall_rate": 0.5228758169934641,
      "precision_rate": 0.16209150326797386
    },
    "0.7": {
      "recall_rate": 0.5228758169934641,
      "precision_rate": 0.1607843137254902
    },
    "0.8": {
      "recall_rate": 0.5163398692810458,
      "precision_rate": 0.15555555555555556
    },
    "0.9": {
      "recall_rate": 0.5163398692810458,
      "precision_rate": 0.13202614379084968
    }
  },
  "recall_mean": 0.5214233841684822,
  "precision_mean": 0.16296296296296298,
  "threshold_discrimination": 0.006535947712418277,
  "threshold_summary": {
    "threshold_auc": 0.5214233841684822,
    "slope": -0.006535947712418277
  },
  "corr_mean": 0.9228842963941761,
  "corr_score": 0.9228842963941761,
  "smoothness_score": 0.8432509374533284,
  "retrieval_score": 0.3364088598402324,
  "plausibility_score": 0.8830676169237522,
  "overall_score": 0.6097382383819923,
  "composite_score": 0.6097382383819923,
  "mrr_mean": 0.4261316872427983,
  "precision_strict": 0.10428467683369642,
  "precision_lift": 0.0,
  "precision_associative": 0.16296296296296298,
  "similarity_recall_rate": 0.5228758169934641,
  "retention_curve": {
    "40": 1.0,
    "80": 1.0,
    "120": 0.6363636363636364,
    "160": 0.5035971223021583,
    "200": 0.5228758169934641
  },
  "retention_auc": 0.7325673151318517,
  "selectivity_score": 0.04560639070442987,
  "robustness_score": 0.0,
  "eval_v2_score": 0.34561752855588374,
  "snapshots": [
    {
      "tick": 0,
      "recall_rate": 1.0,
      "precision_rate": 0.2,
      "activation_recall_correlation": 0.0,
      "fact_episode_delta": 1.0,
      "forgetting_curve_smoothness": 0.0,
      "storage_std": 0.0,
      "storage_iqr": 0.0,
      "storage_gini": 0.0,
      "retrieval_std": 0.0,
      "retrieval_iqr": 0.0,
      "retrieval_gini": 0.0,
      "activation_std": 0.0,
      "activation_iqr": 0.0,
      "activation_gini": 0.0,
      "threshold_metrics": {
        "0.1": {
          "recall_rate": 1.0,
          "precision_rate": 0.2
        },
        "0.2": {
          "recall_rate": 1.0,
          "precision_rate": 0.2
        },
        "0.3": {
          "recall_rate": 1.0,
          "precision_rate": 0.2
        },
        "0.4": {
          "recall_rate": 1.0,
          "precision_rate": 0.2
        },
        "0.5": {
          "recall_rate": 1.0,
          "precision_rate": 0.2
        },
        "0.6": {
          "recall_rate": 1.0,
          "precision_rate": 0.2
        },
        "0.7": {
          "recall_rate": 1.0,
          "precision_rate": 0.2
        },
        "0.8": {
          "recall_rate": 1.0,
          "precision_rate": 0.2
        },
        "0.9": {
          "recall_rate": 1.0,
          "precision_rate": 0.2
        }
      },
      "recall_mean": 1.0,
      "precision_mean": 0.2,
      "threshold_discrimination": 0.0,
      "threshold_summary": {
        "threshold_auc": 1.0,
        "slope": 0.0
      },
      "corr_mean": 0.0,
      "corr_score": 0.0,
      "smoothness_score": 0.5,
      "retrieval_score": 0.5,
      "plausibility_score": 0.25,
      "overall_score": 0.375,
      "composite_score": 0.375,
      "mrr_mean": 0.3333333333333333,
      "precision_strict": 0.2,
      "precision_lift": 0.0,
      "precision_associative": 0.2,
      "similarity_recall_rate": 1.0,
      "retention_curve": {
        "40": 0.0,
        "80": 0.0,
        "120": 0.0,
        "160": 0.0,
        "200": 0.0
      },
      "retention_auc": 0.0,
      "selectivity_score": 0.2,
      "robustness_score": 0.0,
      "eval_v2_score": 0.06999999999999999
    },
    {
      "tick": 20,
      "recall_rate": 1.0,
      "precision_rate": 0.2,
      "activation_recall_correlation": 0.0,
      "fact_episode_delta": 1.0,
      "forgetting_curve_smoothness": 0.0,
      "storage_std": 0.021378230606963124,
      "storage_iqr": 0.0,
      "storage_gini": 0.0011880328361897475,
      "retrieval_std": 0.021378230606963124,
      "retrieval_iqr": 0.0,
      "retrieval_gini": 0.0011880328361897475,
      "activation_std": 0.021378230606963124,
      "activation_iqr": 0.0,
      "activation_gini": 0.0011880328361897475,
      "threshold_metrics": {
        "0.1": {
          "recall_rate": 1.0,
          "precision_rate": 0.2
        },
        "0.2": {
          "recall_rate": 1.0,
          "precision_rate": 0.2
        },
        "0.3": {
          "recall_rate": 1.0,
          "precision_rate": 0.2
        },
        "0.4": {
          "recall_rate": 1.0,
          "precision_rate": 0.2
        },
        "0.5": {
          "recall_rate": 1.0,
          "precision_rate": 0.2
        },
        "0.6": {
          "recall_rate": 1.0,
          "precision_rate": 0.2
        },
        "0.7": {
          "recall_rate": 1.0,
          "precision_rate": 0.2
        },
        "0.8": {
          "recall_rate": 0.0,
          "precision_rate": 0.0
        },
        "0.9": {
          "recall_rate": 0.0,
          "precision_rate": 0.0
        }
      },
      "recall_mean": 0.7777777777777778,
      "precision_mean": 0.15555555555555556,
      "threshold_discrimination": 1.0,
      "threshold_summary": {
        "threshold_auc": 0.7777777777777778,
        "slope": -1.0
      },
      "corr_mean": 0.0,
      "corr_score": 0.0,
      "smoothness_score": 1.0,
      "retrieval_score": 0.5444444444444445,
      "plausibility_score": 0.5,
      "overall_score": 0.5222222222222223,
      "composite_score": 0.5222222222222223,
      "mrr_mean": 0.7777777777777778,
      "precision_strict": 0.15555555555555556,
      "precision_lift": 0.0,
      "precision_associative": 0.15555555555555556,
      "similarity_recall_rate": 1.0,
      "retention_curve": {
        "40": 0.0,
        "80": 0.0,
        "120": 0.0,
        "160": 0.0,
        "200": 0.0
      },
      "retention_auc": 0.0,
      "selectivity_score": 0.15555555555555556,
      "robustness_score": 0.0,
      "eval_v2_score": 0.05444444444444444
    },
    {
      "tick": 40,
      "recall_rate": 1.0,
      "precision_rate": 0.2,
      "activation_recall_correlation": 0.0,
      "fact_episode_delta": 1.0,
      "forgetting_curve_smoothness": 0.0,
      "storage_std": 0.04236212857106994,
      "storage_iqr": 0.0,
      "storage_gini": 0.002608607934494043,
      "retrieval_std": 0.04237096124919861,
      "retrieval_iqr": 0.0,
      "retrieval_gini": 0.0026187300772831197,
      "activation_std": 0.04236212857106994,
      "activation_iqr": 0.0,
      "activation_gini": 0.002608607934494043,
      "threshold_metrics": {
        "0.1": {
          "recall_rate": 1.0,
          "precision_rate": 0.2
        },
        "0.2": {
          "recall_rate": 1.0,
          "precision_rate": 0.2
        },
        "0.3": {
          "recall_rate": 1.0,
          "precision_rate": 0.2
        },
        "0.4": {
          "recall_rate": 1.0,
          "precision_rate": 0.2
        },
        "0.5": {
          "recall_rate": 1.0,
          "precision_rate": 0.2
        },
        "0.6": {
          "recall_rate": 1.0,
          "precision_rate": 0.2
        },
        "0.7": {
          "recall_rate": 1.0,
          "precision_rate": 1.0
        },
        "0.8": {
          "recall_rate": 1.0,
          "precision_rate": 1.0
        },
        "0.9": {
          "recall_rate": 1.0,
          "precision_rate": 1.0
        }
      },
      "recall_mean": 1.0,
      "precision_mean": 0.4666666666666667,
      "threshold_discrimination": 0.0,
      "threshold_summary": {
        "threshold_auc": 1.0,
        "slope": 0.0
      },
      "corr_mean": 0.0,
      "corr_score": 0.0,
      "smoothness_score": 1.0,
      "retrieval_score": 0.7799999999999999,
      "plausibility_score": 0.5,
      "overall_score": 0.6399999999999999,
      "composite_score": 0.6399999999999999,
      "mrr_mean": 1.0,
      "precision_strict": 0.4666666666666667,
      "precision_lift": 0.26666666666666666,
      "precision_associative": 0.4666666666666667,
      "similarity_recall_rate": 1.0,
      "retention_curve": {
        "40": 1.0,
        "80": 0.0,
        "120": 0.0,
        "160": 0.0,
        "200": 0.0
      },
      "retention_auc": 0.2,
      "selectivity_score": 0.4666666666666667,
      "robustness_score": 0.0,
      "eval_v2_score": 0.25333333333333335
    },
    {
      "tick": 60,
      "recall_rate": 1.0,
      "precision_rate": 0.5,
      "activation_recall_correlation": 0.0,
      "fact_episode_delta": 1.0,
      "forgetting_curve_smoothness": 0.0,
      "storage_std": 0.06482174732905228,
      "storage_iqr": 0.0,
      "storage_gini": 0.007218791539150772,
      "retrieval_std": 0.06482174732905228,
      "retrieval_iqr": 0.0,
      "retrieval_gini": 0.007218791539150772,
      "activation_std": 0.06482174732905228,
      "activation_iqr": 0.0,
      "activation_gini": 0.007218791539150772,
      "threshold_metrics": {
        "0.1": {
          "recall_rate": 1.0,
          "precision_rate": 0.5
        },
        "0.2": {
          "recall_rate": 1.0,
          "precision_rate": 0.5
        },
        "0.3": {
          "recall_rate": 1.0,
          "precision_rate": 0.5
        },
        "0.4": {
          "recall_rate": 1.0,
          "precision_rate": 0.5
        },
        "0.5": {
          "recall_rate": 1.0,
          "precision_rate": 0.5
        },
        "0.6": {
          "recall_rate": 1.0,
          "precision_rate": 0.5
        },
        "0.7": {
          "recall_rate": 1.0,
          "precision_rate": 0.5
        },
        "0.8": {
          "recall_rate": 1.0,
          "precision_rate": 0.5
        },
        "0.9": {
          "recall_rate": 0.25,
          "precision_rate": 0.25
        }
      },
      "recall_mean": 0.9166666666666666,
      "precision_mean": 0.4722222222222222,
      "threshold_discrimination": 0.75,
      "threshold_summary": {
        "threshold_auc": 0.9166666666666666,
        "slope": -0.75
      },
      "corr_mean": 0.0,
      "corr_score": 0.0,
      "smoothness_score": 1.0,
      "retrieval_score": 0.5472222222222223,
      "plausibility_score": 0.5,
      "overall_score": 0.5236111111111111,
      "composite_score": 0.5236111111111111,
      "mrr_mean": 0.6018518518518517,
      "precision_strict": 0.18333333333333335,
      "precision_lift": 2.7755575615628914e-17,
      "precision_associative": 0.4722222222222222,
      "similarity_recall_rate": 1.0,
      "retention_curve": {
        "40": 1.0,
        "80": 0.0,
        "120": 0.0,
        "160": 0.0,
        "200": 0.0
      },
      "retention_auc": 0.2,
      "selectivity_score": 0.0,
      "robustness_score": 0.0,
      "eval_v2_score": 0.09000000000000001
    },
    {
      "tick": 80,
      "recall_rate": 1.0,
      "precision_rate": 0.44,
      "activation_recall_correlation": 0.0,
      "fact_episode_delta": 1.0,
      "forgetting_curve_smoothness": 0.0,
      "storage_std": 0.10350537397128538,
      "storage_iqr": 0.0,
      "storage_gini": 0.015088463111718851,
      "retrieval_std": 0.10350537397128538,
      "retrieval_iqr": 0.0,
      "retrieval_gini": 0.015088463111718851,
      "activation_std": 0.10350537397128538,
      "activation_iqr": 0.0,
      "activation_gini": 0.015088463111718851,
      "threshold_metrics": {
        "0.1": {
          "recall_rate": 1.0,
          "precision_rate": 0.44
        },
        "0.2": {
          "recall_rate": 1.0,
          "precision_rate": 0.44
        },
        "0.3": {
          "recall_rate": 1.0,
          "precision_rate": 0.44
        },
        "0.4": {
          "recall_rate": 1.0,
          "precision_rate": 0.44
        },
        "0.5": {
          "recall_rate": 1.0,
          "precision_rate": 0.44
        },
        "0.6": {
          "recall_rate": 1.0,
          "precision_rate": 0.44
        },
        "0.7": {
          "recall_rate": 1.0,
          "precision_rate": 0.44
        },
        "0.8": {
          "recall_rate": 1.0,
          "precision_rate": 0.32
        },
        "0.9": {
          "recall_rate": 0.6,
          "precision_rate": 0.2
        }
      },
      "recall_mean": 0.9555555555555555,
      "precision_mean": 0.4000000000000001,
      "threshold_discrimination": 0.4,
      "threshold_summary": {
        "threshold_auc": 0.9555555555555555,
        "slope": -0.4
      },
      "corr_mean": 0.0,
      "corr_score": 0.0,
      "smoothness_score": 1.0,
      "retrieval_score": 0.5855555555555556,
      "plausibility_score": 0.5,
      "overall_score": 0.5427777777777778,
      "composite_score": 0.5427777777777778,
      "mrr_mean": 0.6777777777777777,
      "precision_strict": 0.19111111111111112,
      "precision_lift": 2.7755575615628914e-17,
      "precision_associative": 0.4000000000000001,
      "similarity_recall_rate": 1.0,
      "retention_curve": {
        "40": 1.0,
        "80": 1.0,
        "120": 0.0,
        "160": 0.0,
        "200": 0.0
      },
      "retention_auc": 0.4,
      "selectivity_score": 0.0,
      "robustness_score": 0.0,
      "eval_v2_score": 0.18000000000000002
    },
    {
      "tick": 100,
      "recall_rate": 1.0,
      "precision_rate": 0.43333333333333335,
      "activation_recall_correlation": 0.0,
      "fact_episode_delta": 1.0,
      "forgetting_curve_smoothness": 0.0,
      "storage_std": 0.12902753766057146,
      "storage_iqr": 0.0,
      "storage_gini": 0.0210006154264263,
      "retrieval_std": 0.1290310175687012,
      "retrieval_iqr": 0.0,
      "retrieval_gini": 0.021003243508526614,
      "activation_std": 0.12902753766057146,
      "activation_iqr": 0.0,
      "activation_gini": 0.0210006154264263,
      "threshold_metrics": {
        "0.1": {
          "recall_rate": 1.0,
          "precision_rate": 0.43333333333333335
        },
        "0.2": {
          "recall_rate": 1.0,
          "precision_rate": 0.43333333333333335
        },
        "0.3": {
          "recall_rate": 1.0,
          "precision_rate": 0.43333333333333335
        },
        "0.4": {
          "recall_rate": 1.0,
          "precision_rate": 0.43333333333333335
        },
        "0.5": {
          "recall_rate": 1.0,
          "precision_rate": 0.43333333333333335
        },
        "0.6": {
          "recall_rate": 1.0,
          "precision_rate": 0.43333333333333335
        },
        "0.7": {
          "recall_rate": 1.0,
          "precision_rate": 0.3333333333333333
        },
        "0.8": {
          "recall_rate": 1.0,
          "precision_rate": 0.3333333333333333
        },
        "0.9": {
          "recall_rate": 0.3333333333333333,
          "precision_rate": 0.13333333333333333
        }
      },
      "recall_mean": 0.925925925925926,
      "precision_mean": 0.37777777777777777,
      "threshold_discrimination": 0.6666666666666667,
      "threshold_summary": {
        "threshold_auc": 0.925925925925926,
        "slope": -0.6666666666666667
      },
      "corr_mean": 0.0,
      "corr_score": 0.0,
      "smoothness_score": 1.0,
      "retrieval_score": 0.5814814814814816,
      "plausibility_score": 0.5,
      "overall_score": 0.5407407407407407,
      "composite_score": 0.5407407407407407,
      "mrr_mean": 0.7037037037037037,
      "precision_strict": 0.1851851851851852,
      "precision_lift": 0.0,
      "precision_associative": 0.37777777777777777,
      "similarity_recall_rate": 1.0,
      "retention_curve": {
        "40": 1.0,
        "80": 1.0,
        "120": 0.0,
        "160": 0.0,
        "200": 0.0
      },
      "retention_auc": 0.4,
      "selectivity_score": 0.0,
      "robustness_score": 0.0,
      "eval_v2_score": 0.18000000000000002
    },
    {
      "tick": 120,
      "recall_rate": 0.6363636363636364,
      "precision_rate": 0.16363636363636364,
      "activation_recall_correlation": 0.26498171579320484,
      "fact_episode_delta": 0.4,
      "forgetting_curve_smoothness": 0.018365472910927456,
      "storage_std": 0.15094448562333998,
      "storage_iqr": 0.0,
      "storage_gini": 0.030001485960084708,
      "retrieval_std": 0.15094625521950747,
      "retrieval_iqr": 0.0,
      "retrieval_gini": 0.03000325286115941,
      "activation_std": 0.15094448562333998,
      "activation_iqr": 0.0,
      "activation_gini": 0.030001485960084708,
      "threshold_metrics": {
        "0.1": {
          "recall_rate": 0.6363636363636364,
          "precision_rate": 0.16363636363636364
        },
        "0.2": {
          "recall_rate": 0.6363636363636364,
          "precision_rate": 0.16363636363636364
        },
        "0.3": {
          "recall_rate": 0.6363636363636364,
          "precision_rate": 0.16363636363636364
        },
        "0.4": {
          "recall_rate": 0.6363636363636364,
          "precision_rate": 0.16363636363636364
        },
        "0.5": {
          "recall_rate": 0.6363636363636364,
          "precision_rate": 0.16363636363636364
        },
        "0.6": {
          "recall_rate": 0.6363636363636364,
          "precision_rate": 0.16363636363636364
        },
        "0.7": {
          "recall_rate": 0.6363636363636364,
          "precision_rate": 0.16363636363636364
        },
        "0.8": {
          "recall_rate": 0.6363636363636364,
          "precision_rate": 0.16363636363636364
        },
        "0.9": {
          "recall_rate": 0.2727272727272727,
          "precision_rate": 0.07272727272727272
        }
      },
      "recall_mean": 0.5959595959595959,
      "precision_mean": 0.15353535353535352,
      "threshold_discrimination": 0.36363636363636365,
      "threshold_summary": {
        "threshold_auc": 0.5959595959595959,
        "slope": -0.36363636363636365
      },
      "corr_mean": 0.3238629661879309,
      "corr_score": 0.3238629661879309,
      "smoothness_score": 0.8163452708907255,
      "retrieval_score": 0.3634343434343434,
      "plausibility_score": 0.5701041185393282,
      "overall_score": 0.46676923098683576,
      "composite_score": 0.46676923098683576,
      "mrr_mean": 0.4168350168350168,
      "precision_strict": 0.11919191919191917,
      "precision_lift": 0.0,
      "precision_associative": 0.15353535353535352,
      "similarity_recall_rate": 0.6363636363636364,
      "retention_curve": {
        "40": 1.0,
        "80": 1.0,
        "120": 0.6363636363636364,
        "160": 0.0,
        "200": 0.0
      },
      "retention_auc": 0.5272727272727272,
      "selectivity_score": 0.08484848484848481,
      "robustness_score": 0.0,
      "eval_v2_score": 0.2669696969696969
    },
    {
      "tick": 140,
      "recall_rate": 0.7083333333333334,
      "precision_rate": 0.30833333333333335,
      "activation_recall_correlation": 0.2803381474091394,
      "fact_episode_delta": 0.3111111111111111,
      "forgetting_curve_smoothness": 0.017894037780401415,
      "storage_std": 0.22838673031666087,
      "storage_iqr": 0.07127035617731625,
      "storage_gini": 0.10498868365673611,
      "retrieval_std": 0.22838772007230923,
      "retrieval_iqr": 0.07127035617731625,
      "retrieval_gini": 0.10498971187789494,
      "activation_std": 0.22838673031666087,
      "activation_iqr": 0.07127035617731625,
      "activation_gini": 0.10498868365673611,
      "threshold_metrics": {
        "0.1": {
          "recall_rate": 0.7083333333333334,
          "precision_rate": 0.30833333333333335
        },
        "0.2": {
          "recall_rate": 0.7083333333333334,
          "precision_rate": 0.30833333333333335
        },
        "0.3": {
          "recall_rate": 0.7083333333333334,
          "precision_rate": 0.30833333333333335
        },
        "0.4": {
          "recall_rate": 0.7083333333333334,
          "precision_rate": 0.30833333333333335
        },
        "0.5": {
          "recall_rate": 0.7083333333333334,
          "precision_rate": 0.30833333333333335
        },
        "0.6": {
          "recall_rate": 0.7083333333333334,
          "precision_rate": 0.30833333333333335
        },
        "0.7": {
          "recall_rate": 0.7083333333333334,
          "precision_rate": 0.30833333333333335
        },
        "0.8": {
          "recall_rate": 0.5,
          "precision_rate": 0.21666666666666667
        },
        "0.9": {
          "recall_rate": 0.20833333333333334,
          "precision_rate": 0.075
        }
      },
      "recall_mean": 0.6296296296296297,
      "precision_mean": 0.27222222222222225,
      "threshold_discrimination": 0.5,
      "threshold_summary": {
        "threshold_auc": 0.6296296296296297,
        "slope": -0.5
      },
      "corr_mean": 0.2133817902896707,
      "corr_score": 0.2133817902896707,
      "smoothness_score": 0.8210596221959858,
      "retrieval_score": 0.36550925925925926,
      "plausibility_score": 0.5172207062428282,
      "overall_score": 0.44136498275104374,
      "composite_score": 0.44136498275104374,
      "mrr_mean": 0.37885802469135804,
      "precision_strict": 0.12592592592592594,
      "precision_lift": 0.0,
      "precision_associative": 0.27222222222222225,
      "similarity_recall_rate": 0.7083333333333334,
      "retention_curve": {
        "40": 1.0,
        "80": 1.0,
        "120": 0.6363636363636364,
        "160": 0.0,
        "200": 0.0
      },
      "retention_auc": 0.5272727272727272,
      "selectivity_score": 0.0,
      "robustness_score": 0.0,
      "eval_v2_score": 0.23727272727272725
    },
    {
      "tick": 160,
      "recall_rate": 0.5035971223021583,
      "precision_rate": 0.1985611510791367,
      "activation_recall_correlation": 0.51644523057318,
      "fact_episode_delta": 0.45548489666136727,
      "forgetting_curve_smoothness": 0.018565747653081534,
      "storage_std": 0.27948141107608393,
      "storage_iqr": 0.42384677426335626,
      "storage_gini": 0.270992359132161,
      "retrieval_std": 0.27943133895136074,
      "retrieval_iqr": 0.42384677426335626,
      "retrieval_gini": 0.27099760946483636,
      "activation_std": 0.27948141107608393,
      "activation_iqr": 0.42384677426335626,
      "activation_gini": 0.270992359132161,
      "threshold_metrics": {
        "0.1": {
          "recall_rate": 0.5035971223021583,
          "precision_rate": 0.1985611510791367
        },
        "0.2": {
          "recall_rate": 0.5035971223021583,
          "precision_rate": 0.1985611510791367
        },
        "0.3": {
          "recall_rate": 0.5035971223021583,
          "precision_rate": 0.1985611510791367
        },
        "0.4": {
          "recall_rate": 0.5035971223021583,
          "precision_rate": 0.1985611510791367
        },
        "0.5": {
          "recall_rate": 0.5035971223021583,
          "precision_rate": 0.1985611510791367
        },
        "0.6": {
          "recall_rate": 0.5035971223021583,
          "precision_rate": 0.1971223021582734
        },
        "0.7": {
          "recall_rate": 0.5035971223021583,
          "precision_rate": 0.18705035971223022
        },
        "0.8": {
          "recall_rate": 0.2805755395683453,
          "precision_rate": 0.09352517985611511
        },
        "0.9": {
          "recall_rate": 0.2517985611510791,
          "precision_rate": 0.07913669064748201
        }
      },
      "recall_mean": 0.45083932853717024,
      "precision_mean": 0.17218225419664268,
      "threshold_discrimination": 0.2517985611510791,
      "threshold_summary": {
        "threshold_auc": 0.45083932853717024,
        "slope": -0.2517985611510791
      },
      "corr_mean": 0.4309074759516275,
      "corr_score": 0.4309074759516275,
      "smoothness_score": 0.8143425234691847,
      "retrieval_score": 0.26850919264588324,
      "plausibility_score": 0.6226249997104061,
      "overall_score": 0.44556709617814466,
      "composite_score": 0.44556709617814466,
      "mrr_mean": 0.2939115374367172,
      "precision_strict": 0.09016786570743406,
      "precision_lift": 1.3877787807814457e-17,
      "precision_associative": 0.17218225419664268,
      "similarity_recall_rate": 0.5035971223021583,
      "retention_curve": {
        "40": 1.0,
        "80": 1.0,
        "120": 0.6363636363636364,
        "160": 0.5035971223021583,
        "200": 0.0
      },
      "retention_auc": 0.6279921517331589,
      "selectivity_score": 0.00815347721822543,
      "robustness_score": 0.0,
      "eval_v2_score": 0.2854501853063004
    },
    {
      "tick": 180,
      "recall_rate": 0.5133333333333333,
      "precision_rate": 0.17866666666666667,
      "activation_recall_correlation": 0.8227322311437983,
      "fact_episode_delta": 0.5137959866220736,
      "forgetting_curve_smoothness": 0.017011855863390792,
      "storage_std": 0.30756639602164376,
      "storage_iqr": 0.54342183612067,
      "storage_gini": 0.41852242763639974,
      "retrieval_std": 0.3071876507141495,
      "retrieval_iqr": 0.54342183612067,
      "retrieval_gini": 0.418258501105793,
      "activation_std": 0.30756639602164376,
      "activation_iqr": 0.54342183612067,
      "activation_gini": 0.41852242763639974,
      "threshold_metrics": {
        "0.1": {
          "recall_rate": 0.5133333333333333,
          "precision_rate": 0.17866666666666667
        },
        "0.2": {
          "recall_rate": 0.5133333333333333,
          "precision_rate": 0.17866666666666667
        },
        "0.3": {
          "recall_rate": 0.5133333333333333,
          "precision_rate": 0.17866666666666667
        },
        "0.4": {
          "recall_rate": 0.5133333333333333,
          "precision_rate": 0.17866666666666667
        },
        "0.5": {
          "recall_rate": 0.5133333333333333,
          "precision_rate": 0.17866666666666667
        },
        "0.6": {
          "recall_rate": 0.5133333333333333,
          "precision_rate": 0.16266666666666665
        },
        "0.7": {
          "recall_rate": 0.5133333333333333,
          "precision_rate": 0.15733333333333333
        },
        "0.8": {
          "recall_rate": 0.4266666666666667,
          "precision_rate": 0.13733333333333334
        },
        "0.9": {
          "recall_rate": 0.2733333333333333,
          "precision_rate": 0.07333333333333333
        }
      },
      "recall_mean": 0.477037037037037,
      "precision_mean": 0.1582222222222222,
      "threshold_discrimination": 0.24,
      "threshold_summary": {
        "threshold_auc": 0.477037037037037,
        "slope": -0.24
      },
      "corr_mean": 0.47722754427165576,
      "corr_score": 0.47722754427165576,
      "smoothness_score": 0.8298814413660921,
      "retrieval_score": 0.30264074074074077,
      "plausibility_score": 0.6535544928188739,
      "overall_score": 0.47809761677980733,
      "composite_score": 0.47809761677980733,
      "mrr_mean": 0.37275308641975313,
      "precision_strict": 0.09540740740740741,
      "precision_lift": 1.3877787807814457e-17,
      "precision_associative": 0.1582222222222222,
      "similarity_recall_rate": 0.5133333333333333,
      "retention_curve": {
        "40": 1.0,
        "80": 1.0,
        "120": 0.6363636363636364,
        "160": 0.5035971223021583,
        "200": 0.0
      },
      "retention_auc": 0.6279921517331589,
      "selectivity_score": 0.03259259259259262,
      "robustness_score": 0.0,
      "eval_v2_score": 0.29400387568732894
    },
    {
      "tick": 200,
      "recall_rate": 0.5228758169934641,
      "precision_rate": 0.17124183006535948,
      "activation_recall_correlation": 0.8844159262584368,
      "fact_episode_delta": 0.543452380952381,
      "forgetting_curve_smoothness": 0.015674906254667158,
      "storage_std": 0.28732567674661247,
      "storage_iqr": 0.5142203271756539,
      "storage_gini": 0.5067254546654726,
      "retrieval_std": 0.2867453491413098,
      "retrieval_iqr": 0.5142203271756539,
      "retrieval_gini": 0.5063104869144508,
      "activation_std": 0.28732567674661247,
      "activation_iqr": 0.5142203271756539,
      "activation_gini": 0.5067254546654726,
      "threshold_metrics": {
        "0.1": {
          "recall_rate": 0.5228758169934641,
          "precision_rate": 0.17124183006535948
        },
        "0.2": {
          "recall_rate": 0.5228758169934641,
          "precision_rate": 0.17124183006535948
        },
        "0.3": {
          "recall_rate": 0.5228758169934641,
          "precision_rate": 0.17124183006535948
        },
        "0.4": {
          "recall_rate": 0.5228758169934641,
          "precision_rate": 0.17124183006535948
        },
        "0.5": {
          "recall_rate": 0.5228758169934641,
          "precision_rate": 0.17124183006535948
        },
        "0.6": {
          "recall_rate": 0.5228758169934641,
          "precision_rate": 0.16209150326797386
        },
        "0.7": {
          "recall_rate": 0.5228758169934641,
          "precision_rate": 0.1607843137254902
        },
        "0.8": {
          "recall_rate": 0.5098039215686274,
          "precision_rate": 0.1542483660130719
        },
        "0.9": {
          "recall_rate": 0.28104575163398693,
          "precision_rate": 0.07581699346405228
        }
      },
      "recall_mean": 0.494553376906318,
      "precision_mean": 0.15657225853304285,
      "threshold_discrimination": 0.24183006535947715,
      "threshold_summary": {
        "threshold_auc": 0.494553376906318,
        "slope": -0.24183006535947715
      },
      "corr_mean": 0.5712556753747342,
      "corr_score": 0.5712556753747342,
      "smoothness_score": 0.8432509374533284,
      "retrieval_score": 0.31903413217138704,
      "plausibility_score": 0.7072533064140313,
      "overall_score": 0.5131437192927092,
      "composite_score": 0.5131437192927092,
      "mrr_mean": 0.40404260469619946,
      "precision_strict": 0.09891067538126361,
      "precision_lift": 0.0,
      "precision_associative": 0.15657225853304285,
      "similarity_recall_rate": 0.5228758169934641,
      "retention_curve": {
        "40": 1.0,
        "80": 1.0,
        "120": 0.6363636363636364,
        "160": 0.5035971223021583,
        "200": 0.5228758169934641
      },
      "retention_auc": 0.7325673151318517,
      "selectivity_score": 0.04124909222948436,
      "robustness_score": 0.0,
      "eval_v2_score": 0.3440924740896528
    }
  ],
  "duration_seconds": 32.33,
  "timing_breakdown": {
    "simulation_seconds": 31.723,
    "final_score_summary_seconds": 3.31,
    "query_similarity_total_seconds": 19.747,
    "query_similarity_call_count": 2448
  }
}